{
  "news__1097": {
    "module": "news",
    "contentId": "-OqAT09TJ9zRamcTiRDc",
    "publicId": "1097",
    "updatedAt": {
      "_seconds": 1776167087,
      "_nanoseconds": 393000000
    }
  },
  "news__1098": {
    "module": "news",
    "contentId": "-OqAXHiRr3saeqhBSGL1",
    "publicId": "1098",
    "updatedAt": {
      "_seconds": 1776167087,
      "_nanoseconds": 393000000
    }
  },
  "news__1101": {
    "module": "news",
    "contentId": "-OqAZAiXH1S63rVVXVUR",
    "publicId": "1101",
    "updatedAt": {
      "_seconds": 1776167087,
      "_nanoseconds": 393000000
    }
  },
  "news__1102": {
    "module": "news",
    "contentId": "-OqAa85DLk9oGBb4E0NB",
    "publicId": "1102",
    "updatedAt": {
      "_seconds": 1776167087,
      "_nanoseconds": 393000000
    }
  },
  "news__1105": {
    "module": "news",
    "contentId": "-OqAqwjNXJ_fudnKJ60a",
    "publicId": "1105",
    "updatedAt": {
      "_seconds": 1776167935,
      "_nanoseconds": 640000000
    }
  },
  "news__1106": {
    "module": "news",
    "contentId": "-OqAwuHShbx-pSM1zG5T",
    "publicId": "1106",
    "updatedAt": {
      "_seconds": 1776169498,
      "_nanoseconds": 970000000
    }
  },
  "news__1107": {
    "module": "news",
    "contentId": "-OqAwuM6KREDC8gBaWSt",
    "publicId": "1107",
    "updatedAt": {
      "_seconds": 1776169499,
      "_nanoseconds": 31000000
    }
  },
  "news__1108": {
    "module": "news",
    "contentId": "-OqAwuR3f4vwnC2sQ5pR",
    "publicId": "1108",
    "updatedAt": {
      "_seconds": 1776169496,
      "_nanoseconds": 196000000
    }
  },
  "news__1109": {
    "module": "news",
    "contentId": "-OqAwuVz_2F9Qnab93o9",
    "publicId": "1109",
    "updatedAt": {
      "_seconds": 1776169497,
      "_nanoseconds": 258000000
    }
  },
  "news__1142": {
    "module": "news",
    "contentId": "-OqEZAuqq-KqRknEllMp",
    "publicId": "1142",
    "createdAt": {
      "_seconds": 1776230124,
      "_nanoseconds": 543000000
    },
    "updatedAt": {
      "_seconds": 1776230124,
      "_nanoseconds": 703000000
    }
  },
  "news__1143": {
    "module": "news",
    "contentId": "-OqEZAz_-aqilfqMBt03",
    "publicId": "1143",
    "createdAt": {
      "_seconds": 1776230126,
      "_nanoseconds": 474000000
    },
    "updatedAt": {
      "_seconds": 1776230126,
      "_nanoseconds": 625000000
    }
  },
  "news__1144": {
    "module": "news",
    "contentId": "-OqEdqFovTpCbjFH-fWq",
    "publicId": "1144",
    "createdAt": {
      "_seconds": 1776231610,
      "_nanoseconds": 41000000
    },
    "updatedAt": {
      "_seconds": 1776231610,
      "_nanoseconds": 782000000
    }
  },
  "news__1153": {
    "module": "news",
    "contentId": "-OqFVgkg6VmbQR-nLXmG",
    "publicId": "1153",
    "createdAt": {
      "_seconds": 1776245989,
      "_nanoseconds": 725000000
    },
    "updatedAt": {
      "_seconds": 1776245990,
      "_nanoseconds": 974000000
    }
  },
  "news__1154": {
    "module": "news",
    "contentId": "-OqFVzHofBL7X3OYhYSM",
    "publicId": "1154",
    "createdAt": {
      "_seconds": 1776246062,
      "_nanoseconds": 315000000
    },
    "updatedAt": {
      "_seconds": 1776246062,
      "_nanoseconds": 481000000
    }
  },
  "news__1155": {
    "module": "news",
    "contentId": "-OqFWYa1uaHYIXK6vPB1",
    "publicId": "1155",
    "createdAt": {
      "_seconds": 1776246209,
      "_nanoseconds": 276000000
    },
    "updatedAt": {
      "_seconds": 1776246210,
      "_nanoseconds": 109000000
    }
  },
  "news__1163": {
    "module": "news",
    "contentId": "-OqFg7kzhU8jE5FwGpQd",
    "publicId": "1163",
    "createdAt": {
      "_seconds": 1776248988,
      "_nanoseconds": 102000000
    },
    "updatedAt": {
      "_seconds": 1776248988,
      "_nanoseconds": 961000000
    }
  },
  "news__1164": {
    "module": "news",
    "contentId": "-OqFkbWs14Q0lTzSa2fY",
    "publicId": "1164",
    "createdAt": {
      "_seconds": 1776250162,
      "_nanoseconds": 428000000
    },
    "updatedAt": {
      "_seconds": 1776250163,
      "_nanoseconds": 210000000
    }
  },
  "news__1166": {
    "module": "news",
    "contentId": "-OqFm3S2OLZkywRdpyAs",
    "publicId": "1166",
    "createdAt": {
      "_seconds": 1776250539,
      "_nanoseconds": 680000000
    },
    "updatedAt": {
      "_seconds": 1776297559,
      "_nanoseconds": 769000000
    }
  },
  "news__1191": {
    "module": "news",
    "contentId": "-OqI_Qf_qXIX77GJgzvD",
    "publicId": "1191",
    "createdAt": {
      "_seconds": 1776297570,
      "_nanoseconds": 20000000
    },
    "updatedAt": {
      "_seconds": 1776297570,
      "_nanoseconds": 170000000
    }
  },
  "news__1192": {
    "module": "news",
    "contentId": "-OqI_Qn0TuikvUyEoWv_",
    "publicId": "1192",
    "createdAt": {
      "_seconds": 1776297568,
      "_nanoseconds": 301000000
    },
    "updatedAt": {
      "_seconds": 1776297568,
      "_nanoseconds": 565000000
    }
  },
  "news__1193": {
    "module": "news",
    "contentId": "-OqI_QrsF5MEituj_7bo",
    "publicId": "1193",
    "createdAt": {
      "_seconds": 1776297571,
      "_nanoseconds": 513000000
    },
    "updatedAt": {
      "_seconds": 1776297572,
      "_nanoseconds": 364000000
    }
  },
  "news__1194": {
    "module": "news",
    "contentId": "-OqI_Qx79Ji0dLnWgtTs",
    "publicId": "1194",
    "createdAt": {
      "_seconds": 1776297566,
      "_nanoseconds": 549000000
    },
    "updatedAt": {
      "_seconds": 1776297566,
      "_nanoseconds": 839000000
    }
  },
  "news__248": {
    "module": "news",
    "contentId": "-Oq9S7ZOAoAFXHRNbfSg",
    "publicId": "248",
    "updatedAt": {
      "_seconds": 1776167087,
      "_nanoseconds": 393000000
    }
  },
  "news__250": {
    "module": "news",
    "contentId": "-Oq9ScxqCW9076tsixBd",
    "publicId": "250",
    "updatedAt": {
      "_seconds": 1776167087,
      "_nanoseconds": 393000000
    }
  }
}